globalfactordata/__init__.py
globalfactordata/download_link.py
globalfactordata/getdata.py
globalfactordata/loader.py
globalfactordata/test.py
globalfactordata/data/Cluster Labels.csv
globalfactordata/data/Country Classification.xlsx
globalfactordata/data/Factor Details.xlsx
globalfactordata/data/data_url.pkl
globalfactordata-0.1.0.dist-info/METADATA
globalfactordata-0.1.0.dist-info/WHEEL
globalfactordata-0.1.0.dist-info/top_level.txt
globalfactordata-0.1.0.dist-info/RECORD
