Metadata-Version: 2.4
Name: globalfactordata
Version: 0.1.0
Summary: JKP 글로벌 팩터 데이터를 쉽게 불러올 수 있는 도구
Home-page: https://github.com/hyunyulhenry/globalfactordata
Author: Henry Lee
Classifier: Programming Language :: Python :: 3
Classifier: Operating System :: OS Independent
Requires-Python: >=3.7
Requires-Dist: pandas
Requires-Dist: openpyxl
Dynamic: author
Dynamic: classifier
Dynamic: description
Dynamic: description-content-type
Dynamic: home-page
Dynamic: requires-dist
Dynamic: requires-python
Dynamic: summary
